Workbook

Sheet Assumptions
A1: WBS Cost Model — Assumptions & Rate Card
A2: Blue cells = inputs you can change | Black cells = calculated | All costs in USD
A4: RATE CARD
A5: Role | B5: Onshore ($/hr) | C5: Offshore ($/hr) | D5: Onshore ($/pd) | E5: Offshore ($/pd) | F5: Notes
A6: Engagement Director | B6: 195 | C6: — | D6: =B6*8 -> 1560 | E6: — | F6: Onshore only
A7: Solution Architect | B7: 175 | C7: 68 | D7: =B7*8 -> 1400 | E7: =C7*8 -> 544
A8: Senior Data/ML Engineer | B8: 145 | C8: 52 | D8: =B8*8 -> 1160 | E8: =C8*8 -> 416 | F8: Databricks certified
A9: Data/Analytics Engineer | B9: 115 | C9: 38 | D9: =B9*8 -> 920 | E9: =C9*8 -> 304
A10: DataOps/Platform Engineer | B10: 125 | C10: 42 | D10: =B10*8 -> 1000 | E10: =C10*8 -> 336
A11: BA / Governance Lead | B11: 95 | C11: 30 | D11: =B11*8 -> 760 | E11: =C11*8 -> 240
A12: QA / Data Steward | B12: 85 | C12: 25 | D12: =B12*8 -> 680 | E12: =C12*8 -> 200
A14: DELIVERY MODEL
A15: Offshore ratio | B15: 0.83
A16: Onshore ratio | B16: =1-B15 -> 0.17
A17: Working days per month | B17: 21
A18: Hours per day | B18: 8
A19: Coordination buffer % | B19: 0.05
A22: BLENDED RATE CALCULATION
A23: Avg onshore rate ($/hr) | B23: =AVERAGE(B6:B12) -> 133.57143
A24: Avg offshore rate ($/hr) | B24: =AVERAGEIF(C6:C12,">0") -> 42.5
A25: Avg onshore rate ($/pd) | B25: =B23*B18 -> 1068.5714
A26: Avg offshore rate ($/pd) | B26: =B24*B18 -> 340
A27: BLENDED RATE ($/hr) | B27: =B16*B23+B15*B24 -> 57.982143
A28: BLENDED RATE ($/pd) | B28: =B16*B25+B15*B26 -> 463.85714
A31: PHASE PARAMETERS
A32: Parameter | B32: Phase 1 | C32: Phase 2 | D32: Phase 3 | E32: Total
A33: Duration (months) | B33: 4 | C33: 6 | D33: 6 | E33: =SUM(B33:D33) -> 16
A34: Onshore FTE (peak) | B34: 5 | C34: 4 | D34: 4 | E34: =SUM(B34:D34) -> 13
A35: Offshore FTE (peak) | B35: 13 | C35: 18 | D35: 14 | E35: =SUM(B35:D35) -> 45
A36: Total FTE (peak) | B36: =B34+B35 -> 18 | C36: =C34+C35 -> 22 | D36: =D34+D35 -> 18 | E36: =MAX(B36,C36,D36) -> 22
A37: Effort — deliverables (pd) | B37: 2100 | C37: 2900 | D37: 2300 | E37: =SUM(B37:D37) -> 7300
A38: Coordination buffer (5%) (pd) | B38: =ROUND(B37*Assumptions!$B$19,0) -> 105 | C38: =ROUND(C37*Assumptions!$B$19,0) -> 145 | D38: =ROUND(D37*Assumptions!$B$19,0) -> 115 | E38: =SUM(B38:D38) -> 365
A39: TOTAL EFFORT (incl. buffer) (pd) | B39: =B37+B38 -> 2205 | C39: =C37+C38 -> 3045 | D39: =D37+D38 -> 2415 | E39: =SUM(B39:D39) -> 7665
A40: PHASE COST ($) | B40: =B39*Assumptions!$B$28 -> 1022805 | C40: =C39*Assumptions!$B$28 -> 1412445 | D40: =D39*Assumptions!$B$28 -> 1120215 | E40: =SUM(B40:D40) -> 3555465

Sheet WBS Detail
A1: Work Breakdown Structure - Detailed Cost Model
A2: Blue = inputs | Black = formulas | Costs = Effort (pd) × Blended Rate from Assumptions sheet
A4: WBS ID | B4: Deliverable / Work Package | C4: Phase | D4: Lead Role | E4: Offshore Ratio | F4: Effort (pd) | G4: Onshore pd | H4: Offshore pd | I4: Cost ($) @ blended rate | J4: Notes
A5: 1.0 | B5: Platform & Infrastructure | C5: 1 | D5: Cloud Architect | E5: 0.7 | F5: =SUM(F6:F13) -> 700 | G5: =ROUND(F5*(1-E5),0) -> 210 | H5: =ROUND(F5*E5,0) -> 490 | I5: =SUM(I6:I13) -> 324700 | J5: AWS foundation + IaC baseline
A6: 1.1 | B6: AWS VPC, IAM, Direct Connect, Security Groups | C6: 1 | D6: Cloud Architect | E6: 0.6 | F6: 80 | G6: =ROUND(F6*(1-E6),0) -> 32 | H6: =ROUND(F6*E6,0) -> 48 | I6: =F6*Assumptions!$B$28 -> 37108.571 | J6: On-prem to cloud connectivity
A7: 1.2 | B7: Databricks Workspace + Unity Catalog setup | C7: 1 | D7: Platform Lead | E7: 0.8 | F7: 120 | G7: =ROUND(F7*(1-E7),0) -> 24 | H7: =ROUND(F7*E7,0) -> 96 | I7: =F7*Assumptions!$B$28 -> 55662.857 | J7: Cluster config, UC admin, workspace isolation
A8: 1.3 | B8: Terraform IaC + CI/CD baseline (DEV→SIT→UAT→PROD) | C8: 1 | D8: DataOps Engineer | E8: 0.85 | F8: 80 | G8: =ROUND(F8*(1-E8),0) -> 12 | H8: =ROUND(F8*E8,0) -> 68 | I8: =F8*Assumptions!$B$28 -> 37108.571 | J8: Infra as code, pipeline templates
A9: 1.4 | B9: Security hardening - AWS WAF, GuardDuty, CloudTrail | C9: 1 | D9: Cloud Architect | E9: 0.8 | F9: 80 | G9: =ROUND(F9*(1-E9),0) -> 16 | H9: =ROUND(F9*E9,0) -> 64 | I9: =F9*Assumptions!$B$28 -> 37108.571 | J9: Security posture, VPC flow logs, audit trail
A10: 1.5 | B10: Multi-region HA - Active-Active across 2 AWS regions | C10: 1 | D10: Platform Lead | E10: 0.75 | F10: 120 | G10: =ROUND(F10*(1-E10),0) -> 30 | H10: =ROUND(F10*E10,0) -> 90 | I10: =F10*Assumptions!$B$28 -> 55662.857 | J10: S3 CRR, Databricks multi-region workspace config
A11: 1.6 | B11: Monitoring & alerting - Databricks Lakehouse Monitoring | C11: 1 | D11: DataOps Engineer | E11: 0.85 | F11: 80 | G11: =ROUND(F11*(1-E11),0) -> 12 | H11: =ROUND(F11*E11,0) -> 68 | I11: =F11*Assumptions!$B$28 -> 37108.571 | J11: Pipeline health, DQ drift, SLA alerting
A12: 1.7 | B12: Performance baseline testing & cluster tuning | C12: 1 | D12: Platform Lead | E12: 0.8 | F12: 80 | G12: =ROUND(F12*(1-E12),0) -> 16 | H12: =ROUND(F12*E12,0) -> 64 | I12: =F12*Assumptions!$B$28 -> 37108.571 | J12: Photon tuning, cluster policies, auto-scaling validation
A13: 1.8 | B13: Environment management (DEV / SIT / UAT / PROD) | C13: 1 | D13: DataOps Engineer | E13: 0.85 | F13: 60 | G13: =ROUND(F13*(1-E13),0) -> 9 | H13: =ROUND(F13*E13,0) -> 51 | I13: =F13*Assumptions!$B$28 -> 27831.429 | J13: Workspace-per-env, feature branch CI/CD
A14: 2.0 | B14: Data Ingestion & Migration | C14: 1-2 | D14: Sr Data Engineer | E14: 0.85 | F14: =SUM(F15:F20) -> 920 | G14: =ROUND(F14*(1-E14),0) -> 138 | H14: =ROUND(F14*E14,0) -> 782 | I14: =SUM(I15:I20) -> 426748.57 | J14: CDC + historical + streaming
A15: 2.1 | B15: SAP HANA + MDM CDC pipelines (AWS DMS) | C15: 1 | D15: Sr Data Engineer | E15: 0.85 | F15: 180 | G15: =ROUND(F15*(1-E15),0) -> 27 | H15: =ROUND(F15*E15,0) -> 153 | I15: =F15*Assumptions!$B$28 -> 83494.286 | J15: Full + incremental extract via DMS
A16: 2.2 | B16: Historical data load - ~5 years backfill | C16: 1 | D16: Data Engineer | E16: 0.9 | F16: 200 | G16: =ROUND(F16*(1-E16),0) -> 20 | H16: =ROUND(F16*E16,0) -> 180 | I16: =F16*Assumptions!$B$28 -> 92771.429 | J16: Auto Loader batch ingest to Bronze
A17: 2.3 | B17: Streaming pipelines - Kinesis + DLT | C17: 2 | D17: Sr Data Engineer | E17: 0.85 | F17: 180 | G17: =ROUND(F17*(1-E17),0) -> 27 | H17: =ROUND(F17*E17,0) -> 153 | I17: =F17*Assumptions!$B$28 -> 83494.286 | J17: Real-time event ingest <500ms
A18: 2.4 | B18: Data profiling & source system analysis sprint | C18: 1 | D18: Sr Data Engineer | E18: 0.85 | F18: 120 | G18: =ROUND(F18*(1-E18),0) -> 18 | H18: =ROUND(F18*E18,0) -> 102 | I18: =F18*Assumptions!$B$28 -> 55662.857 | J18: Schema discovery, volume analysis, DQ baseline
A19: 2.5 | B19: MDM system integration + master data pipelines | C19: 1 | D19: Sr Data Engineer | E19: 0.85 | F19: 120 | G19: =ROUND(F19*(1-E19),0) -> 18 | H19: =ROUND(F19*E19,0) -> 102 | I19: =F19*Assumptions!$B$28 -> 55662.857 | J19: Product, customer, supplier master data CDC
A20: 2.6 | B20: Data quality gate implementation (DLT Expectations) | C20: 2 | D20: Sr Data Engineer | E20: 0.85 | F20: 120 | G20: =ROUND(F20*(1-E20),0) -> 18 | H20: =ROUND(F20*E20,0) -> 102 | I20: =F20*Assumptions!$B$28 -> 55662.857 | J20: Warn/drop/fail rules across all ingestion pipelines
A21: 3.0 | B21: Medallion Lakehouse (Bronze → Silver → Gold) | C21: 1-2 | D21: Data Engineer | E21: 0.85 | F21: =SUM(F22:F29) -> 1160 | G21: =ROUND(F21*(1-E21),0) -> 174 | H21: =ROUND(F21*E21,0) -> 986 | I21: =SUM(I22:I29) -> 538074.29 | J21: Core Delta Lake zones
A22: 3.1 | B22: Bronze zone - raw ingestion layer | C22: 1 | D22: Data Engineer | E22: 0.9 | F22: 120 | G22: =ROUND(F22*(1-E22),0) -> 12 | H22: =ROUND(F22*E22,0) -> 108 | I22: =F22*Assumptions!$B$28 -> 55662.857 | J22: Schema enforcement, DLT Expectations
A23: 3.2 | B23: Silver zone - cleanse, conform, deduplicate | C23: 1-2 | D23: Data Engineer | E23: 0.85 | F23: 200 | G23: =ROUND(F23*(1-E23),0) -> 30 | H23: =ROUND(F23*E23,0) -> 170 | I23: =F23*Assumptions!$B$28 -> 92771.429 | J23: DQ rules, SCD2, cross-source joins
A24: 3.3 | B24: Gold zone - 6 domain data products | C24: 2 | D24: Data Engineer + BA | E24: 0.8 | F24: 200 | G24: =ROUND(F24*(1-E24),0) -> 40 | H24: =ROUND(F24*E24,0) -> 160 | I24: =F24*Assumptions!$B$28 -> 92771.429 | J24: Supply Chain, Brand, Consumer, Margin, Home Care, Beauty
A25: 3.4 | B25: Delta Live Tables pipeline orchestration (all zones) | C25: 1-2 | D25: Data Engineer | E25: 0.85 | F25: 160 | G25: =ROUND(F25*(1-E25),0) -> 24 | H25: =ROUND(F25*E25,0) -> 136 | I25: =F25*Assumptions!$B$28 -> 74217.143 | J25: Full DLT DAG design, dependency mgmt, retry logic
A26: 3.5 | B26: Data partitioning, Z-ordering & performance optimisation | C26: 2 | D26: Data Engineer | E26: 0.85 | F26: 120 | G26: =ROUND(F26*(1-E26),0) -> 18 | H26: =ROUND(F26*E26,0) -> 102 | I26: =F26*Assumptions!$B$28 -> 55662.857 | J26: Partition strategy per domain, vacuum, OPTIMIZE jobs
A27: 3.6 | B27: Schema registry & schema evolution management | C27: 1-2 | D27: Data Engineer | E27: 0.85 | F27: 100 | G27: =ROUND(F27*(1-E27),0) -> 15 | H27: =ROUND(F27*E27,0) -> 85 | I27: =F27*Assumptions!$B$28 -> 46385.714 | J27: Schema versioning, backward compat, auto-schema inference
A28: 3.7 | B28: Time travel, CDC merge patterns & SCD2 implementation | C28: 2 | D28: Data Engineer | E28: 0.85 | F28: 120 | G28: =ROUND(F28*(1-E28),0) -> 18 | H28: =ROUND(F28*E28,0) -> 102 | I28: =F28*Assumptions!$B$28 -> 55662.857 | J28: MERGE INTO, SCD2 for slowly changing dimensions
A29: 3.8 | B29: Data lineage mapping across all 6 domain products | C29: 2 | D29: Governance Lead | E29: 0.7 | F29: 140 | G29: =ROUND(F29*(1-E29),0) -> 42 | H29: =ROUND(F29*E29,0) -> 98 | I29: =F29*Assumptions!$B$28 -> 64940 | J29: Unity Catalog lineage, column-level impact analysis
A30: 4.0 | B30: Analytics, BI & ML Platform | C30: 2-3 | D30: Analytics + ML Pod | E30: 0.8 | F30: =SUM(F31:F39) -> 1740 | G30: =ROUND(F30*(1-E30),0) -> 348 | H30: =ROUND(F30*E30,0) -> 1392 | I30: =SUM(I31:I39) -> 807111.43 | J30: Full analytics + ML stack
A31: 4.1 | B31: BI connectivity + semantic layer (Power BI / Tableau) | C31: 2 | D31: BI Developer | E31: 0.85 | F31: 240 | G31: =ROUND(F31*(1-E31),0) -> 36 | H31: =ROUND(F31*E31,0) -> 204 | I31: =F31*Assumptions!$B$28 -> 111325.71 | J31: Direct Lake mode, certified datasets
A32: 4.2 | B32: Supply chain analytics - 5 use cases | C32: 2 | D32: Analyst + Data Scientist | E32: 0.8 | F32: 280 | G32: =ROUND(F32*(1-E32),0) -> 56 | H32: =ROUND(F32*E32,0) -> 224 | I32: =F32*Assumptions!$B$28 -> 129880 | J32: Demand, inventory, supplier, logistics, margin
A33: 4.3 | B33: ML platform - MLflow + Feature Store + Model Serving | C33: 3 | D33: ML Engineer | E33: 0.8 | F33: 300 | G33: =ROUND(F33*(1-E33),0) -> 60 | H33: =ROUND(F33*E33,0) -> 240 | I33: =F33*Assumptions!$B$28 -> 139157.14 | J33: Training pipelines, registry, deployment
A34: 4.4 | B34: Demand forecasting + margin analytics models | C34: 3 | D34: Data Scientist | E34: 0.8 | F34: 160 | G34: =ROUND(F34*(1-E34),0) -> 32 | H34: =ROUND(F34*E34,0) -> 128 | I34: =F34*Assumptions!$B$28 -> 74217.143 | J34: Phase 3 ML models in production
A35: 4.5 | B35: e-Influence analytics domain - data product design & build | C35: 3 | D35: Data Scientist | E35: 0.8 | F35: 200 | G35: =ROUND(F35*(1-E35),0) -> 40 | H35: =ROUND(F35*E35,0) -> 160 | I35: =F35*Assumptions!$B$28 -> 92771.429 | J35: Digital signal to shelf offtake attribution model
A36: 4.6 | B36: Self-serve SQL layer - certified dataset publishing | C36: 2 | D36: BI Developer | E36: 0.85 | F36: 120 | G36: =ROUND(F36*(1-E36),0) -> 18 | H36: =ROUND(F36*E36,0) -> 102 | I36: =F36*Assumptions!$B$28 -> 55662.857 | J36: Power BI Direct Lake, certified dataset governance
A37: 4.7 | B37: ML Feature Store setup + feature engineering pipelines | C37: 3 | D37: ML Engineer | E37: 0.8 | F37: 160 | G37: =ROUND(F37*(1-E37),0) -> 32 | H37: =ROUND(F37*E37,0) -> 128 | I37: =F37*Assumptions!$B$28 -> 74217.143 | J37: Feature definitions, versioning, online/offline serving
A38: 4.8 | B38: Model monitoring & drift detection - production MLOps | C38: 3 | D38: ML Engineer | E38: 0.8 | F38: 120 | G38: =ROUND(F38*(1-E38),0) -> 24 | H38: =ROUND(F38*E38,0) -> 96 | I38: =F38*Assumptions!$B$28 -> 55662.857 | J38: Lakehouse Monitoring, retraining triggers
A39: 4.9 | B39: Dashboard UAT, sign-off & hypercare (all BI workstreams) | C39: 2-3 | D39: BI Developer | E39: 0.8 | F39: 160 | G39: =ROUND(F39*(1-E39),0) -> 32 | H39: =ROUND(F39*E39,0) -> 128 | I39: =F39*Assumptions!$B$28 -> 74217.143 | J39: Client UAT support, defect resolution, go-live prep
A40: 5.0 | B40: Governance, Security & Compliance | C40: 1-3 | D40: Governance Lead | E40: 0.75 | F40: =SUM(F41:F47) -> 900 | G40: =ROUND(F40*(1-E40),0) -> 225 | H40: =ROUND(F40*E40,0) -> 675 | I40: =SUM(I41:I47) -> 417471.43 | J40: Unity Catalog + multi-region compliance
A41: 5.1 | B41: Unity Catalog RBAC, masking, tagging setup | C41: 1 | D41: Governance Lead | E41: 0.7 | F41: 160 | G41: =ROUND(F41*(1-E41),0) -> 48 | H41: =ROUND(F41*E41,0) -> 112 | I41: =F41*Assumptions!$B$28 -> 74217.143 | J41: Row/column policies, PII tags, lineage
A42: 5.2 | B42: Data Steward programme - onboarding + certification | C42: 2 | D42: BA / Governance Lead | E42: 0.8 | F42: 160 | G42: =ROUND(F42*(1-E42),0) -> 32 | H42: =ROUND(F42*E42,0) -> 128 | I42: =F42*Assumptions!$B$28 -> 74217.143 | J42: Data Steward roles, glossary, ownership
A43: 5.3 | B43: Compliance framework - GDPR, CCPA, PDPA, PIPL, LGPD | C43: 2-3 | D43: Governance Lead | E43: 0.75 | F43: 160 | G43: =ROUND(F43*(1-E43),0) -> 40 | H43: =ROUND(F43*E43,0) -> 120 | I43: =F43*Assumptions!$B$28 -> 74217.143 | J43: Regional workspace isolation, audit logs
A44: 5.4 | B44: Data classification & sensitivity tagging (all domains) | C44: 1-2 | D44: Governance Lead | E44: 0.75 | F44: 120 | G44: =ROUND(F44*(1-E44),0) -> 30 | H44: =ROUND(F44*E44,0) -> 90 | I44: =F44*Assumptions!$B$28 -> 55662.857 | J44: PII, confidential, public tags via Unity Catalog
A45: 5.5 | B45: Data product SLA & chargeback instrumentation | C45: 2 | D45: DataOps Engineer | E45: 0.8 | F45: 120 | G45: =ROUND(F45*(1-E45),0) -> 24 | H45: =ROUND(F45*E45,0) -> 96 | I45: =F45*Assumptions!$B$28 -> 55662.857 | J45: DBU metering per BU, S3 cost allocation tagging
A46: 5.6 | B46: Audit logging, access reviews & compliance reporting | C46: 2-3 | D46: Governance Lead | E46: 0.75 | F46: 100 | G46: =ROUND(F46*(1-E46),0) -> 25 | H46: =ROUND(F46*E46,0) -> 75 | I46: =F46*Assumptions!$B$28 -> 46385.714 | J46: Monthly access reports, GDPR audit trail
A47: 5.7 | B47: Data Mesh operating model documentation & playbooks | C47: 2 | D47: BA / Governance Lead | E47: 0.8 | F47: 80 | G47: =ROUND(F47*(1-E47),0) -> 16 | H47: =ROUND(F47*E47,0) -> 64 | I47: =F47*Assumptions!$B$28 -> 37108.571 | J47: Domain ownership, data product contracts, RACI
A48: 6.0 | B48: Quick Win - Supply Chain KPI Dashboard | C48: 1 | D48: BI Developer + DE | E48: 0.8 | F48: =SUM(F49:F51) -> 200 | G48: =ROUND(F48*(1-E48),0) -> 40 | H48: =ROUND(F48*E48,0) -> 160 | I48: =SUM(I49:I51) -> 92771.429 | J48: Month 3 delivery target
A49: 6.1 | B49: Supply Chain domain Bronze + Silver ingest | C49: 1 | D49: Data Engineer | E49: 0.9 | F49: 80 | G49: =ROUND(F49*(1-E49),0) -> 8 | H49: =ROUND(F49*E49,0) -> 72 | I49: =F49*Assumptions!$B$28 -> 37108.571 | J49: 2 source systems, DLT pipeline
A50: 6.2 | B50: Demand domain Bronze + Silver ingest | C50: 1 | D50: Data Engineer | E50: 0.9 | F50: 60 | G50: =ROUND(F50*(1-E50),0) -> 6 | H50: =ROUND(F50*E50,0) -> 54 | I50: =F50*Assumptions!$B$28 -> 27831.429 | J50: Forecast inputs, historical demand
A51: 6.3 | B51: Power BI KPI dashboard - 5 report packs | C51: 1 | D51: BI Developer | E51: 0.8 | F51: 60 | G51: =ROUND(F51*(1-E51),0) -> 12 | H51: =ROUND(F51*E51,0) -> 48 | I51: =F51*Assumptions!$B$28 -> 27831.429 | J51: Replaces 5 manual weekly Excel reports
A52: 7.0 | B52: Capability Building | C52: 1-3 | D52: BA / Governance Lead | E52: 0.8 | F52: =SUM(F53:F58) -> 500 | G52: =ROUND(F52*(1-E52),0) -> 100 | H52: =ROUND(F52*E52,0) -> 400 | I52: =SUM(I53:I58) -> 231928.57 | J52: Embedded training workstream
A53: 7.1 | B53: Self-serve SQL bootcamp - brand managers | C53: 2 | D53: BA / Governance Lead | E53: 0.8 | F53: 80 | G53: =ROUND(F53*(1-E53),0) -> 16 | H53: =ROUND(F53*E53,0) -> 64 | I53: =F53*Assumptions!$B$28 -> 37108.571 | J53: SQL basics, Databricks SQL UI, certified datasets
A54: 7.2 | B54: Data Steward certification programme | C54: 2 | D54: BA / Governance Lead | E54: 0.8 | F54: 80 | G54: =ROUND(F54*(1-E54),0) -> 16 | H54: =ROUND(F54*E54,0) -> 64 | I54: =F54*Assumptions!$B$28 -> 37108.571 | J54: Governance tools, ownership, quality gates
A55: 7.3 | B55: ML literacy programme - analytics teams | C55: 3 | D55: BA / Governance Lead | E55: 0.8 | F55: 80 | G55: =ROUND(F55*(1-E55),0) -> 16 | H55: =ROUND(F55*E55,0) -> 64 | I55: =F55*Assumptions!$B$28 -> 37108.571 | J55: AutoML, feature engineering, model consumption
A56: 7.4 | B56: Centre of Excellence handover + documentation | C56: 3 | D56: BA / Governance Lead | E56: 0.8 | F56: 60 | G56: =ROUND(F56*(1-E56),0) -> 12 | H56: =ROUND(F56*E56,0) -> 48 | I56: =F56*Assumptions!$B$28 -> 27831.429 | J56: Runbooks, standards, CoE governance model
A57: 7.5 | B57: Change management & stakeholder comms programme | C57: 1-3 | D57: BA / Governance Lead | E57: 0.6 | F57: 120 | G57: =ROUND(F57*(1-E57),0) -> 48 | H57: =ROUND(F57*E57,0) -> 72 | I57: =F57*Assumptions!$B$28 -> 55662.857 | J57: Comms plan, exec updates, user adoption tracking
A58: 7.6 | B58: Data literacy baseline assessment & gap analysis | C58: 1 | D58: BA / Governance Lead | E58: 0.7 | F58: 80 | G58: =ROUND(F58*(1-E58),0) -> 24 | H58: =ROUND(F58*E58,0) -> 56 | I58: =F58*Assumptions!$B$28 -> 37108.571 | J58: Skills assessment across 3 divisions, training roadmap
A59: 8.0 | B59: KT, Hypercare & Runbooks | C59: 3 | D59: All Leads | E59: 0.7 | F59: =SUM(F60:F65) -> 400 | G59: =ROUND(F59*(1-E59),0) -> 120 | H59: =ROUND(F59*E59,0) -> 280 | I59: =SUM(I60:I65) -> 185542.86 | J59: End-of-programme handover
A60: 8.1 | B60: Knowledge transfer sessions (all workstreams) | C60: 3 | D60: All Leads | E60: 0.7 | F60: 80 | G60: =ROUND(F60*(1-E60),0) -> 24 | H60: =ROUND(F60*E60,0) -> 56 | I60: =F60*Assumptions!$B$28 -> 37108.571 | J60: Structured KT workshops with client team
A61: 8.2 | B61: Runbook + operational documentation | C61: 3 | D61: DataOps Engineer | E61: 0.8 | F61: 40 | G61: =ROUND(F61*(1-E61),0) -> 8 | H61: =ROUND(F61*E61,0) -> 32 | I61: =F61*Assumptions!$B$28 -> 18554.286 | J61: Platform ops, incident playbooks
A62: 8.3 | B62: Hypercare support - first 30 days post go-live | C62: 3 | D62: All Leads | E62: 0.65 | F62: 40 | G62: =ROUND(F62*(1-E62),0) -> 14 | H62: =ROUND(F62*E62,0) -> 26 | I62: =F62*Assumptions!$B$28 -> 18554.286 | J62: Triage, bug fixes, performance tuning
A63: 8.4 | B63: Platform operations handover - runbooks & SOP library | C63: 3 | D63: DataOps Engineer | E63: 0.8 | F63: 80 | G63: =ROUND(F63*(1-E63),0) -> 16 | H63: =ROUND(F63*E63,0) -> 64 | I63: =F63*Assumptions!$B$28 -> 37108.571 | J63: Incident playbooks, on-call procedures, SLA mgmt
A64: 8.5 | B64: Production support - 60-day hypercare window | C64: 3 | D64: All Leads | E64: 0.65 | F64: 100 | G64: =ROUND(F64*(1-E64),0) -> 35 | H64: =ROUND(F64*E64,0) -> 65 | I64: =F64*Assumptions!$B$28 -> 46385.714 | J64: L2/L3 support, performance tuning, user queries
A65: 8.6 | B65: Post-implementation review & optimisation recommendations | C65: 3 | D65: Solution Architect | E65: 0.5 | F65: 60 | G65: =ROUND(F65*(1-E65),0) -> 30 | H65: =ROUND(F65*E65,0) -> 30 | I65: =F65*Assumptions!$B$28 -> 27831.429 | J65: PIR report, Phase 4 roadmap recommendations
A67: WBS TOTAL | B67: All 53 deliverable work packages | E67: =SUMPRODUCT(F5:F66,E5:E66)/SUM(F5:F66) -> 0.79578221 | F67: =F5+F14+F21+F30+F40+F48+F52+F59 -> 6520 | G67: =G5+G14+G21+G30+G40+G48+G52+G59 -> 1355 | H67: =H5+H14+H21+H30+H40+H48+H52+H59 -> 5165 | I67: =I5+I14+I21+I30+I40+I48+I52+I59 -> 3024348.6 | J67: excl. overhead & buffer
A69: PROGRAMME COST RECONCILIATION - How WBS cost builds to total programme cost
A70: Component | B70: Person-days | C70: Rate ($/pd) | D70: Cost ($) | J70: Explanation
A71: WBS deliverable effort | B71: =F67 -> 6520 | C71: =Assumptions!$B$28 -> 463.85714 | D71: =B71*C71 -> 3024348.6 | J71: 53 defined work packages - full deliverable scope
A72: Programme overhead | B72: 780 | C72: =Assumptions!$B$28 -> 463.85714 | D72: =B72*C72 -> 361808.57 | J72: Agile ceremonies, code reviews, deployment, team management (12.0% of deliverables - industry standard 10-15%)
A73: Coordination buffer (5%) | B73: =ROUND((B71+B72)*Assumptions!$B$19,0) -> 365 | C73: =Assumptions!$B$28 -> 463.85714 | D73: =B73*C73 -> 169307.86 | J73: 5% buffer on total deliverable + overhead effort
A74: TOTAL PROGRAMME COST | B74: =B71+B72+B73 -> 7665 | C74: =Assumptions!$B$28 -> 463.85714 | D74: =B74*C74 -> 3555465 | J74: Phase Summary total | Blended $464/pd | 83% offshore / 17% onshore

Sheet Phase Summary
A1: Phase Cost & Effort Summary
A2: All values flow from WBS Detail and Assumptions sheets
A4: Metric | B4: Phase 1 | C4: Phase 2 | D4: Phase 3 | E4: Buffer | F4: Total | G4: Notes
A5: Duration (months) | B5: =Assumptions!B33 -> 4 | C5: =Assumptions!C33 -> 6 | D5: =Assumptions!D33 -> 6
A6: Peak FTE (total) | B6: =Assumptions!B36 -> 18 | C6: =Assumptions!C36 -> 22 | D6: =Assumptions!D36 -> 18
A7: Effort - deliverables (pd) | B7: =Assumptions!B37 -> 2100 | C7: =Assumptions!C37 -> 2900 | D7: =Assumptions!D37 -> 2300 | E7: =Assumptions!E38 -> 365 | F7: =Assumptions!E37 -> 7300
A8: Coordination buffer (pd) | B8: =Assumptions!B38 -> 105 | C8: =Assumptions!C38 -> 145 | D8: =Assumptions!D38 -> 115 | F8: =Assumptions!E38 -> 365
A9: Total effort incl. buffer (pd) | B9: =Assumptions!B39 -> 2205 | C9: =Assumptions!C39 -> 3045 | D9: =Assumptions!D39 -> 2415 | E9: =Assumptions!E38 -> 365 | F9: =Assumptions!E39 -> 7665
A10: Phase cost ($) | B10: =Assumptions!B40 -> 1022805 | C10: =Assumptions!C40 -> 1412445 | D10: =Assumptions!D40 -> 1120215 | E10: =Assumptions!E38 -> 365 | F10: =Assumptions!E40 -> 3555465
A12: Engagement model: Phase 1 = Fixed Price | Phase 2 = T&M | Phase 3 = T&M | Blended rate = 80% offshore / 20% onshore at $58/hr ($464/pd)
